opencamlib/STLTools.py
opencamlib/__init__.py
opencamlib/camvtk.py
opencamlib/libomp.dylib
opencamlib/ocl.so
opencamlib/procmemory.py
opencamlib/pyocl.py
opencamlib-2023.1.11.dist-info/METADATA
opencamlib-2023.1.11.dist-info/WHEEL
opencamlib-2023.1.11.dist-info/entry_points.txt
opencamlib-2023.1.11.dist-info/RECORD
