Metadata-Version: 2.1
Name: opencamlib
Version: 2023.1.11
Summary: open source computer aided manufacturing algorithms library
Keywords: cam cnc waterline axial tool projection
Home-page: https://github.com/aewallin/opencamlib
Author-Email: Anders Wallin <anders.e.e.wallin@gmail.com>
Maintainer-Email: Koen Schmeets <koen@schmeets.de>
License:                   GNU LESSER GENERAL PUBLIC LICENSE
